PeekDir/__init__.py
PeekDir/cli.py
PeekDir-0.2.0.dist-info/LICENSE.md
PeekDir-0.2.0.dist-info/METADATA
PeekDir-0.2.0.dist-info/WHEEL
PeekDir-0.2.0.dist-info/entry_points.txt
PeekDir-0.2.0.dist-info/top_level.txt
PeekDir-0.2.0.dist-info/RECORD
